synodal.py
synodal-25.10.0.dist-info/METADATA
synodal-25.10.0.dist-info/WHEEL
synodal-25.10.0.dist-info/licenses/COPYING
synodal-25.10.0.dist-info/RECORD
