Metadata-Version: 2.4
Name: synodal
Version: 25.10.0
Summary: Metadata about the Synodalsoft project
Project-URL: Homepage, https://www.synodalsoft.net
Project-URL: Repository, https://gitlab.com/lino-framework/synodal
Author-email: Rumma & Ko Ltd <info@lino-framework.org>
License:                     GNU AFFERO GENERAL PUBLIC LICENSE
License-File: COPYING
Classifier: Development Status :: 4 - Beta
Classifier: Intended Audience :: Developers
Classifier: License :: OSI Approved :: GNU Affero General Public License v3
Classifier: Natural Language :: English
Classifier: Operating System :: OS Independent
Classifier: Programming Language :: Python
Classifier: Programming Language :: Python :: 3
